spotipy/__init__.py
spotipy/client.py
spotipy/oauth2.py
spotipy/util.py
ndelnano_spotipy-1.0.1.dist-info/LICENSE.txt
ndelnano_spotipy-1.0.1.dist-info/METADATA
ndelnano_spotipy-1.0.1.dist-info/WHEEL
ndelnano_spotipy-1.0.1.dist-info/top_level.txt
ndelnano_spotipy-1.0.1.dist-info/RECORD
