Metadata-Version: 2.1
Name: ndelnano-spotipy
Version: 1.0.1
Summary: simple client for the Spotify Web API, adding mysql for token storage/access
Home-page: http://spotipy.readthedocs.org/
Author: @ndelnano
Author-email: nickdelnano@gmail.com
License: LICENSE.txt
Platform: UNKNOWN
Requires-Dist: requests (>=2.3.0)
Requires-Dist: six (>=1.10.0)
Requires-Dist: mysqlclient
